basic_algorithm/__init__.py
basic_algorithm/array_of_difference.py
basic_algorithm/binary_lifting.py
basic_algorithm/binary_search.py
character_string/prefix_function.py
character_string/z_function.py
data_structure/bit.py
data_structure/dsu.py
data_structure/monotonic_queue.py
data_structure/monotonic_stack.py
data_structure/segment_tree.py
data_structure/stack.py
dynamic_programming/digital_dp.py
graph/__init__.py
graph/bfs.py
graph/binary_search_tree.py
graph/binary_tree.py
graph/find_circle.py
graph/km_algorithm.py
graph/lca.py
graph/minimum_spanning_tree.py
graph/smallest_routes.py
graph/topological_sorting.py
mathematic/combinatorics.py
mathematic/common_formula.py
mathematic/fast_power.py
mathematic/fermat_little_theorem.py
mathematic/filter_prime.py
mathematic/find_prime_factor.py
mathematic/greatest_common_divisor.py
mathematic/judge_prime.py
misc/__init__.py
misc/bootstrap.py
misc/discretization.py
misc/double_pointer.py
python_contest_template/__init__.py
python_contest_template/binary_tree.py
python_contest_template/single_linked_list.py
search/backtrace.py
python_contest_template-0.0.7.dist-info/LICENSE
python_contest_template-0.0.7.dist-info/METADATA
python_contest_template-0.0.7.dist-info/WHEEL
python_contest_template-0.0.7.dist-info/top_level.txt
python_contest_template-0.0.7.dist-info/RECORD
