Metadata-Version: 2.1
Name: python_contest_template
Version: 0.0.7
Summary: python template for contest
Author-email: zhangtingyu11 <zhangty21@mails.jlu.edu.cn>
Project-URL: Homepage, https://github.com/zhangtingyu11/python_contest_template
Project-URL: Bug Tracker, https://github.com/zhangtingyu11/python_contest_template/issues
Classifier: Programming Language :: Python :: 3
Classifier: License :: OSI Approved :: MIT License
Classifier: Operating System :: OS Independent
Requires-Python: >=3.10
License-File: LICENSE
Requires-Dist: pytest
Requires-Dist: pytest-html
Requires-Dist: pytest-xdist
Requires-Dist: pytest-ordering
Requires-Dist: pytest-rerunfailures
Requires-Dist: allure-pytest
